README.md
setup.cfg
setup.py
tests/__init__.py
tests/test_losses.py
tests/backend/__init__.py
tests/backend/test_common.py
tests/layers/__init__.py
tests/layers/test_filter_detections.py
tests/layers/test_misc.py
tests/models/__init__.py
tests/models/test_densenet.py
tests/models/test_mobilenet.py
tests/preprocessing/__init__.py
tests/preprocessing/test_csv_generator.py
tests/preprocessing/test_generator.py
tests/utils/__init__.py
tests/utils/test_anchors.py
tests/utils/test_transform.py
xmenu_keras_retinanet/__init__.py
xmenu_keras_retinanet/initializers.py
xmenu_keras_retinanet/losses.py
xmenu_keras_retinanet.egg-info/PKG-INFO
xmenu_keras_retinanet.egg-info/SOURCES.txt
xmenu_keras_retinanet.egg-info/dependency_links.txt
xmenu_keras_retinanet.egg-info/entry_points.txt
xmenu_keras_retinanet.egg-info/requires.txt
xmenu_keras_retinanet.egg-info/top_level.txt
xmenu_keras_retinanet/backend/__init__.py
xmenu_keras_retinanet/backend/cntk_backend.py
xmenu_keras_retinanet/backend/common.py
xmenu_keras_retinanet/backend/dynamic.py
xmenu_keras_retinanet/backend/tensorflow_backend.py
xmenu_keras_retinanet/backend/theano_backend.py
xmenu_keras_retinanet/bin/__init__.py
xmenu_keras_retinanet/bin/convert_model.py
xmenu_keras_retinanet/bin/debug.py
xmenu_keras_retinanet/bin/evaluate.py
xmenu_keras_retinanet/bin/train.py
xmenu_keras_retinanet/callbacks/__init__.py
xmenu_keras_retinanet/callbacks/coco.py
xmenu_keras_retinanet/callbacks/common.py
xmenu_keras_retinanet/callbacks/eval.py
xmenu_keras_retinanet/layers/__init__.py
xmenu_keras_retinanet/layers/_misc.py
xmenu_keras_retinanet/layers/filter_detections.py
xmenu_keras_retinanet/models/__init__.py
xmenu_keras_retinanet/models/densenet.py
xmenu_keras_retinanet/models/effnet.py
xmenu_keras_retinanet/models/mobilenet.py
xmenu_keras_retinanet/models/resnet.py
xmenu_keras_retinanet/models/retinanet.py
xmenu_keras_retinanet/models/senet.py
xmenu_keras_retinanet/models/vgg.py
xmenu_keras_retinanet/preprocessing/__init__.py
xmenu_keras_retinanet/preprocessing/coco.py
xmenu_keras_retinanet/preprocessing/csv_generator.py
xmenu_keras_retinanet/preprocessing/generator.py
xmenu_keras_retinanet/preprocessing/kitti.py
xmenu_keras_retinanet/preprocessing/open_images.py
